README.md
setup.py
shibboleth_get.py
shibboleth_get.egg-info/PKG-INFO
shibboleth_get.egg-info/SOURCES.txt
shibboleth_get.egg-info/dependency_links.txt
shibboleth_get.egg-info/entry_points.txt
shibboleth_get.egg-info/requires.txt
shibboleth_get.egg-info/top_level.txt