Metadata-Version: 1.1
Name: shibboleth-get
Version: 0.1.0
Summary: Get the content of pages shielded by Shibboleth
Home-page: https://github.com/MatthewScholefield/shibboleth-get
Author: Matthew D. Scholefield
Author-email: matthew331199@gmail.com
License: UNKNOWN
Keywords: shibboleth get
Platform: UNKNOWN
Classifier: Development Status :: 3 - Alpha
Classifier: Intended Audience :: Developers
Classifier: Programming Language :: Python :: 3
Classifier: Programming Language :: Python :: 3.4
Classifier: Programming Language :: Python :: 3.5
Classifier: Programming Language :: Python :: 3.6
